rafael_nn/__init__.py
rafael_nn/acfn.py
rafael_nn/common.py
rafael_nn/layer.py
rafael_nn/lossfn.py
rafael_nn/nn.py
rafael_nn/optimizer.py
rafael_nn-1.0.0.dist-info/METADATA
rafael_nn-1.0.0.dist-info/WHEEL
rafael_nn-1.0.0.dist-info/top_level.txt
rafael_nn-1.0.0.dist-info/RECORD
