Metadata-Version: 2.4
Name: rafael_nn
Version: 1.0.0
Summary: A minimal nn with numpy for DL-UCV 1-2025
Author-email: Rafael Contreras <rcontreraspimentel@gmail.com>
Requires-Python: >=3.8
Requires-Dist: numpy
